src/somos/somos.py
somos-0.0.0.dist-info/METADATA
somos-0.0.0.dist-info/WHEEL
somos-0.0.0.dist-info/licenses/LICENSE
somos-0.0.0.dist-info/RECORD
