Metadata-Version: 2.1
Name: somos
Version: 0.0.0
Summary: A somos sequence generator for Python!
Project-URL: Documentation, http://somos.rtfd.io/
Project-URL: Homepage, https://github.com/Pigeon43/somos
Project-URL: Issues / Bugs, https://github.com/Pigeon43/somos/issues
Project-URL: PyPI, https://pypi.org/project/somos/
Project-URL: Support Server, https://discord.gg/MyPTZBH4Q8
Project-URL: Wikipedia Page, https://en.wikipedia.org/wiki/Somos_sequence
Author-email: thatgaypigeon <rapidpigeon43@gmail.com>
License: The MIT License (MIT)
License-File: LICENSE
Keywords: equation,math,maths,number,numbers,oeis,recurrence,recurrence relation,sequence,somos
Classifier: Development Status :: 5 - Production/Stable
Classifier: Intended Audience :: Developers
Classifier: License :: OSI Approved
Classifier: License :: OSI Approved :: MIT License
Classifier: Natural Language :: English
Classifier: Operating System :: OS Independent
Classifier: Programming Language :: Python
Classifier: Programming Language :: Python :: 3.8
Classifier: Programming Language :: Python :: 3.9
Classifier: Programming Language :: Python :: 3.10
Classifier: Programming Language :: Python :: 3.11
Classifier: Topic :: Other/Nonlisted Topic
Classifier: Topic :: Scientific/Engineering
Classifier: Topic :: Scientific/Engineering :: Mathematics
Classifier: Topic :: Software Development
Classifier: Topic :: Software Development :: Libraries
Classifier: Topic :: Software Development :: Libraries :: Python Modules
Classifier: Typing :: Typed
Requires-Python: >=3.8
